tests/__init__.py
tests/config.py
tests/common/__init__.py
tests/common/test_data_explorer.py
tests/core/__init__.py
tests/core/test_config.py
tests/core/test_converter.py
tests/core/test_utils.py
tests/explorer/__init__.py
tests/explorer/fmarket/__init__.py
tests/explorer/fmarket/test_fund.py
tests/explorer/misc/__init__.py
tests/explorer/misc/test_exchange_rate.py
tests/explorer/misc/test_gold_price.py
tests/explorer/msn/__init__.py
tests/explorer/msn/test_quote.py
tests/explorer/tcbs/__init__.py
tests/explorer/tcbs/test_analysis.py
tests/explorer/tcbs/test_company.py
tests/explorer/tcbs/test_quote.py
tests/explorer/vci/__init__.py
tests/explorer/vci/test_analysis.py
tests/explorer/vci/test_company.py
tests/explorer/vci/test_financial.py
tests/explorer/vci/test_quote.py
vnstock3/__init__.py
vnstock3/botbuilder/__init__.py
vnstock3/botbuilder/noti.py
vnstock3/common/__init__.py
vnstock3/common/cli.py
vnstock3/common/vnstock.py
vnstock3/common/data/__init__.py
vnstock3/common/data/data_explorer.py
vnstock3/common/plot/__init__.py
vnstock3/common/plot/chart_wrapper.py
vnstock3/core/__init__.py
vnstock3/core/config/__init__.py
vnstock3/core/config/auth.py
vnstock3/core/config/const.py
vnstock3/core/converter/__init__.py
vnstock3/core/converter/export.py
vnstock3/core/utils/__init__.py
vnstock3/core/utils/env.py
vnstock3/core/utils/ext.py
vnstock3/core/utils/help.py
vnstock3/core/utils/launcher.py
vnstock3/core/utils/logger.py
vnstock3/core/utils/parser.py
vnstock3/core/utils/upgrade.py
vnstock3/core/utils/user_agent.py
vnstock3/explorer/__init__.py
vnstock3/explorer/fmarket/__init__.py
vnstock3/explorer/fmarket/const.py
vnstock3/explorer/fmarket/fund.py
vnstock3/explorer/misc/__init__.py
vnstock3/explorer/misc/exchange_rate.py
vnstock3/explorer/misc/gold_price.py
vnstock3/explorer/msn/__init__.py
vnstock3/explorer/msn/const.py
vnstock3/explorer/msn/helper.py
vnstock3/explorer/msn/listing.py
vnstock3/explorer/msn/models.py
vnstock3/explorer/msn/quote.py
vnstock3-3.1.0.dist-info/LICENSE.md
vnstock3-3.1.0.dist-info/METADATA
vnstock3-3.1.0.dist-info/WHEEL
vnstock3-3.1.0.dist-info/entry_points.txt
vnstock3-3.1.0.dist-info/top_level.txt
vnstock3-3.1.0.dist-info/RECORD
