Metadata-Version: 2.1
Name: vnstock3
Version: 3.1.0
Summary: A comprehensive and transparent solution for Vietnamese stock market analysis.
Home-page: https://github.com/thinh-vu/vnstock
Author: Thinh Vu
Author-email: Thinh Vu <vnstock.hq@gmail.com>
License: **GIẤY PHÉP SỬ DỤNG PHẦN MỀM VNSTOCK3**
Project-URL: Homepage, https://github.com/thinh-vu/vnstock
Classifier: Programming Language :: Python :: 3
Classifier: License :: OSI Approved :: MIT License
Classifier: Operating System :: OS Independent
Requires-Python: >=3.10
License-File: LICENSE.md
Requires-Dist: requests
Requires-Dist: beautifulsoup4
Requires-Dist: pandas
Requires-Dist: vnai>=0.1.3
Requires-Dist: openpyxl
Requires-Dist: pydantic
Requires-Dist: psutil
Requires-Dist: fake_useragent
Requires-Dist: vnstock_ezchart
Requires-Dist: click
Requires-Dist: seaborn
Provides-Extra: dev
Requires-Dist: flake8; extra == "dev"
Provides-Extra: docs
Requires-Dist: sphinx; extra == "docs"
Requires-Dist: sphinx_rtd_theme; extra == "docs"
Provides-Extra: test
Requires-Dist: unittest; extra == "test"
